googletrans/__init__.py
googletrans/client.py
googletrans/constants.py
googletrans/gtoken.py
googletrans/models.py
googletrans/urls.py
googletrans/utils.py
googletrans_wheel2_py-4.0.0.dist-info/LICENSE
googletrans_wheel2_py-4.0.0.dist-info/METADATA
googletrans_wheel2_py-4.0.0.dist-info/WHEEL
googletrans_wheel2_py-4.0.0.dist-info/top_level.txt
googletrans_wheel2_py-4.0.0.dist-info/RECORD
