Metadata-Version: 2.1
Name: googletrans-wheel2-py
Version: 4.0.0
Summary: Free Google Translate API for Python. Translates totally free of charge.
Home-page: https://github.com/StarkBotsIndustries/googletrans
Author: StarkProgrammer
Author-email: starkbotsindustries@gmail.com
License: MIT
Keywords: google translate translator
Classifier: Development Status :: 5 - Production/Stable
Classifier: Intended Audience :: Education
Classifier: Intended Audience :: End Users/Desktop
Classifier: License :: Freeware
Classifier: Operating System :: POSIX
Classifier: Operating System :: Microsoft :: Windows
Classifier: Operating System :: MacOS :: MacOS X
Classifier: Topic :: Education
Classifier: Programming Language :: Python
Classifier: Programming Language :: Python :: 3.7
Classifier: Programming Language :: Python :: 3.8
Classifier: Programming Language :: Python :: 3.9
Classifier: Programming Language :: Python :: 3.10
Requires-Python: >=3.7
License-File: LICENSE
Requires-Dist: httpx >=0.22.0
Requires-Dist: h2 <5,>=4
